{"type":{"0":"projection","1":"projection","2":"projection","3":"projection","4":"projection","5":"projection","6":"projection","7":"projection","8":"projection","9":"projection","10":"projection","11":"projection","12":"projection","13":"projection","14":"projection","15":"projection","16":"projection","17":"projection","18":"projection","19":"projection","20":"projection","21":"projection","22":"projection","23":"projection","24":"projection","25":"projection","26":"projection","27":"projection","28":"projection","29":"projection","30":"projection","31":"projection","32":"projection","33":"projection","34":"projection","35":"projection","36":"projection","37":"projection","38":"projection","39":"projection","40":"projection","41":"projection","42":"projection","43":"projection","44":"projection","45":"projection","46":"projection","47":"projection","48":"projection","49":"projection","50":"projection","51":"projection","52":"projection","53":"projection","54":"projection","55":"projection","56":"projection","57":"projection","58":"projection","59":"projection","60":"projection","61":"projection","62":"projection","63":"projection","64":"projection","65":"projection","66":"projection","67":"projection","68":"projection","69":"projection","70":"projection","71":"projection","72":"projection","73":"projection","74":"projection","75":"projection","76":"projection","77":"projection","78":"projection","79":"projection","80":"projection","81":"projection","82":"projection","83":"projection","84":"projection","85":"projection","86":"projection","87":"projection","88":"projection","89":"projection","90":"projection","91":"projection","92":"projection","93":"projection","94":"projection","95":"projection","96":"projection","97":"projection","98":"projection","99":"projection","100":"projection","101":"projection","102":"projection","103":"projection","104":"projection","105":"projection","106":"projection","107":"projection","108":"projection","109":"projection","110":"projection","111":"projection","112":"projection","113":"projection","114":"projection","115":"projection","116":"projection","117":"projection","118":"projection","119":"projection","120":"projection","121":"projection","122":"projection","123":"projection","124":"projection","125":"projection","126":"projection","127":"projection","128":"projection","129":"projection","130":"projection","131":"projection","132":"projection","133":"projection","134":"projection","135":"projection","136":"projection","137":"projection","138":"projection","139":"projection","140":"projection","141":"projection","142":"projection","143":"projection","144":"projection","145":"projection","146":"projection","147":"projection","148":"projection","149":"projection","150":"projection","151":"projection","152":"projection","153":"projection","154":"projection","155":"projection","156":"projection","157":"projection","158":"projection","159":"projection","160":"projection","161":"projection","162":"projection","163":"projection","164":"projection","165":"projection","166":"projection","167":"projection","168":"projection","169":"projection","170":"projection","171":"projection","172":"projection","173":"projection","174":"projection","175":"projection","176":"projection","177":"projection","178":"projection","179":"projection","180":"projection","181":"projection","182":"projection","183":"projection","184":"projection","185":"projection","186":"projection","187":"projection","188":"projection","189":"projection","190":"projection","191":"projection","192":"projection","193":"projection","194":"projection","195":"projection","196":"projection","197":"projection","198":"projection","199":"projection","200":"projection","201":"projection","202":"projection","203":"projection","204":"projection","205":"projection","206":"projection","207":"projection","208":"projection","209":"projection","210":"projection","211":"projection","212":"projection","213":"projection","214":"projection","215":"projection","216":"projection","217":"projection","218":"projection","219":"projection","220":"projection","221":"projection","222":"projection","223":"projection","224":"projection","225":"projection","226":"projection","227":"projection","228":"projection","229":"projection","230":"projection","231":"projection","232":"projection","233":"projection","234":"projection","235":"projection","236":"projection","237":"projection","238":"projection","239":"projection","240":"projection","241":"projection","242":"projection","243":"projection","244":"projection","245":"projection","246":"projection","247":"projection","248":"projection","249":"projection","250":"projection","251":"projection","252":"projection","253":"projection","254":"projection","255":"projection","256":"projection","257":"projection","258":"projection","259":"projection","260":"projection","261":"projection","262":"projection","263":"projection","264":"projection","265":"projection","266":"projection","267":"projection","268":"projection","269":"projection","270":"projection","271":"projection","272":"projection","273":"projection","274":"projection","275":"projection","276":"projection","277":"projection","278":"projection","279":"projection","280":"projection","281":"projection","282":"projection","283":"projection","284":"projection","285":"projection","286":"projection","287":"projection","288":"projection","289":"projection","290":"projection","291":"projection","292":"projection","293":"projection","294":"projection","295":"projection","296":"projection","297":"projection","298":"projection","299":"projection","300":"projection","301":"projection","302":"projection","303":"projection","304":"projection","305":"projection","306":"projection","307":"projection","308":"projection","309":"projection","310":"projection","311":"projection","312":"projection","313":"projection","314":"projection","315":"projection","316":"projection","317":"projection","318":"projection","319":"projection","320":"projection","321":"projection","322":"projection","323":"projection","324":"projection","325":"projection","326":"projection","327":"projection","328":"projection","329":"projection","330":"projection","331":"projection","332":"projection","333":"projection","334":"projection","335":"projection","336":"projection","337":"projection","338":"projection","339":"projection","340":"projection","341":"projection","342":"projection","343":"projection","344":"projection","345":"projection","346":"projection","347":"projection","348":"projection","349":"projection","350":"projection","351":"projection","352":"projection","353":"projection","354":"projection","355":"projection","356":"projection","357":"projection","358":"projection","359":"projection","360":"projection","361":"projection","362":"projection","363":"projection","364":"projection","365":"projection","366":"projection","367":"projection","368":"projection","369":"projection","370":"projection","371":"projection","372":"projection","373":"projection","374":"projection","375":"projection","376":"projection","377":"projection","378":"projection","379":"projection","380":"projection","381":"projection","382":"projection","383":"projection","384":"projection","385":"projection","386":"projection","387":"projection","388":"projection","389":"projection","390":"projection","391":"projection","392":"projection","393":"projection","394":"projection","395":"projection","396":"projection","397":"projection","398":"projection","399":"projection","400":"projection","401":"projection","402":"projection","403":"projection","404":"projection","405":"projection","406":"projection","407":"projection","408":"projection","409":"projection","410":"projection","411":"projection","412":"projection","413":"projection","414":"projection","415":"projection","416":"projection","417":"projection","418":"projection","419":"projection","420":"projection","421":"projection","422":"projection","423":"projection","424":"projection","425":"projection","426":"projection","427":"projection","428":"projection","429":"projection","430":"projection","431":"projection","432":"projection","433":"projection","434":"projection","435":"projection","436":"projection","437":"projection","438":"projection","439":"projection","440":"projection","441":"projection","442":"projection","443":"projection","444":"projection","445":"projection","446":"projection","447":"projection","448":"projection","449":"projection","450":"projection","451":"projection","452":"projection","453":"projection","454":"projection","455":"projection","456":"projection","457":"projection","458":"projection","459":"projection","460":"projection","461":"projection","462":"projection","463":"projection","464":"projection","465":"projection","466":"projection","467":"projection","468":"projection","469":"projection","470":"projection","471":"projection","472":"projection","473":"projection","474":"projection","475":"projection","476":"projection","477":"projection","478":"projection","479":"projection","480":"projection","481":"projection","482":"projection","483":"projection","484":"projection","485":"projection","486":"projection","487":"projection","488":"projection","489":"projection","490":"projection","491":"projection","492":"projection","493":"projection","494":"projection","495":"projection","496":"projection","497":"projection","498":"projection","499":"projection","500":"projection","501":"projection","502":"projection","503":"projection","504":"projection","505":"projection","506":"projection","507":"projection","508":"projection","509":"projection","510":"projection","511":"projection","512":"projection","513":"projection","514":"projection","515":"projection","516":"projection","517":"projection","518":"projection","519":"projection","520":"projection","521":"projection","522":"projection","523":"projection","524":"projection","525":"projection","526":"projection","527":"projection","528":"projection","529":"projection","530":"projection","531":"projection","532":"projection","533":"projection","534":"projection","535":"projection","536":"projection","537":"projection","538":"projection","539":"projection","540":"projection","541":"projection","542":"projection","543":"projection","544":"projection","545":"projection","546":"projection","547":"projection","548":"projection","549":"projection","550":"projection","551":"projection","552":"projection","553":"projection","554":"projection","555":"projection","556":"projection","557":"projection","558":"projection","559":"projection","560":"projection","561":"projection","562":"projection","563":"projection","564":"projection","565":"projection","566":"projection","567":"projection","568":"projection","569":"projection","570":"projection","571":"projection","572":"projection","573":"projection","574":"projection","575":"projection","576":"projection","577":"projection","578":"projection","579":"projection","580":"projection","581":"projection","582":"projection","583":"projection","584":"projection","585":"projection","586":"projection","587":"projection","588":"projection","589":"projection","590":"projection","591":"projection","592":"projection","593":"projection"},"description":{"0":"LAC\/HOU","1":"LAC\/HOU","2":"LAC\/HOU","3":"OKC\/PHX","4":"OKC\/PHX","5":"SAC\/MIN","6":"SAC\/MIN","7":"SAC\/MIN","8":"MEM\/GSW","9":"MEM\/GSW","10":"MEM\/GSW","11":"HOU","12":"HOU","13":"HOU","14":"HOU","15":"HOU","16":"HOU","17":"HOU","18":"HOU","19":"HOU","20":"LAC","21":"LAC","22":"LAC","23":"LAC","24":"LAC","25":"LAC","26":"LAC","27":"LAC","28":"LAC","29":"LAC","30":"HOU","31":"HOU","32":"HOU","33":"HOU","34":"HOU","35":"HOU","36":"HOU","37":"HOU","38":"LAC","39":"LAC","40":"LAC","41":"LAC","42":"LAC","43":"LAC","44":"LAC","45":"LAC","46":"LAC","47":"LAC","48":"LAC","49":"HOU","50":"HOU","51":"HOU","52":"HOU","53":"HOU","54":"HOU","55":"HOU","56":"HOU","57":"LAC","58":"LAC","59":"LAC","60":"LAC","61":"LAC","62":"LAC","63":"LAC","64":"LAC","65":"LAC","66":"LAC","67":"HOU","68":"HOU","69":"LAC","70":"LAC","71":"LAC","72":"LAC","73":"LAC","74":"LAC","75":"LAC","76":"LAC","77":"LAC","78":"LAC","79":"LAC","80":"LAC","81":"LAC","82":"LAC","83":"LAC","84":"LAC","85":"LAC","86":"LAC","87":"LAC","88":"LAC","89":"LAC","90":"LAC","91":"LAC","92":"LAC","93":"LAC","94":"LAC","95":"LAC","96":"LAC","97":"LAC","98":"LAC","99":"LAC","100":"LAC","101":"LAC","102":"LAC","103":"LAC","104":"LAC","105":"LAC","106":"LAC","107":"LAC","108":"LAC","109":"LAC","110":"LAC","111":"LAC","112":"LAC","113":"LAC","114":"LAC","115":"LAC","116":"LAC","117":"LAC","118":"LAC","119":"LAC","120":"LAC","121":"LAC","122":"LAC","123":"LAC","124":"LAC","125":"LAC","126":"LAC","127":"LAC","128":"LAC","129":"LAC","130":"LAC","131":"LAC","132":"LAC","133":"LAC","134":"LAC","135":"LAC","136":"LAC","137":"LAC","138":"LAC","139":"LAC","140":"LAC","141":"LAC","142":"LAC","143":"LAC","144":"LAC","145":"LAC","146":"LAC","147":"LAC","148":"LAC","149":"LAC","150":"LAC","151":"LAC","152":"NOP","153":"NOP","154":"NOP","155":"NOP","156":"NOP","157":"NOP","158":"NOP","159":"DEN","160":"DEN","161":"DEN","162":"DEN","163":"NOP","164":"NOP","165":"NOP","166":"NOP","167":"DEN","168":"DEN","169":"DEN","170":"DEN","171":"DEN","172":"DEN","173":"DEN","174":"NOP","175":"NOP","176":"DEN","177":"DEN","178":"DEN","179":"DEN","180":"NOP","181":"NOP","182":"NOP","183":"NOP","184":"NOP","185":"NOP","186":"DEN","187":"DEN","188":"DEN","189":"NOP","190":"NOP","191":"NOP","192":"DEN","193":"DEN","194":"DEN","195":"DEN","196":"DEN","197":"DEN","198":"DEN","199":"DEN","200":"NOP","201":"NOP","202":"NOP","203":"DEN","204":"DEN","205":"DEN","206":"DEN","207":"DEN","208":"DEN","209":"DEN","210":"OKC","211":"OKC","212":"OKC","213":"OKC","214":"OKC","215":"OKC","216":"PHX","217":"PHX","218":"PHX","219":"PHX","220":"PHX","221":"OKC","222":"OKC","223":"OKC","224":"OKC","225":"OKC","226":"OKC","227":"PHX","228":"PHX","229":"PHX","230":"PHX","231":"PHX","232":"OKC","233":"OKC","234":"OKC","235":"OKC","236":"OKC","237":"PHX","238":"PHX","239":"PHX","240":"PHX","241":"PHX","242":"PHX","243":"OKC","244":"OKC","245":"PHX","246":"PHX","247":"PHX","248":"PHX","249":"PHX","250":"PHX","251":"PHX","252":"PHX","253":"OKC","254":"OKC","255":"OKC","256":"OKC","257":"PHX","258":"PHX","259":"PHX","260":"OKC","261":"OKC","262":"OKC","263":"OKC","264":"OKC","265":"PHX","266":"OKC","267":"OKC","268":"PHX","269":"PHX","270":"PHX","271":"OKC","272":"OKC","273":"OKC","274":"OKC","275":"PHX","276":"PHX","277":"PHX","278":"PHX","279":"PHX","280":"PHX","281":"PHX","282":"OKC","283":"OKC","284":"OKC","285":"OKC","286":"OKC","287":"OKC","288":"OKC","289":"OKC","290":"PHX","291":"SAC","292":"SAC","293":"SAC","294":"SAC","295":"SAC","296":"SAC","297":"SAC","298":"SAC","299":"SAC","300":"SAC","301":"SAC","302":"SAC","303":"MIN","304":"MIN","305":"MIN","306":"MIN","307":"MIN","308":"MIN","309":"MIN","310":"MIN","311":"MIN","312":"MIN","313":"MIN","314":"MIN","315":"SAC","316":"SAC","317":"SAC","318":"SAC","319":"SAC","320":"SAC","321":"SAC","322":"SAC","323":"SAC","324":"SAC","325":"SAC","326":"MIN","327":"MIN","328":"MIN","329":"MIN","330":"MIN","331":"MIN","332":"MIN","333":"MIN","334":"MIN","335":"MIN","336":"MIN","337":"SAC","338":"SAC","339":"SAC","340":"SAC","341":"SAC","342":"SAC","343":"SAC","344":"SAC","345":"MIN","346":"MIN","347":"MIN","348":"MIN","349":"MIN","350":"MIN","351":"MIN","352":"MIN","353":"SAC","354":"SAC","355":"SAC","356":"SAC","357":"SAC","358":"SAC","359":"SAC","360":"MIN","361":"MIN","362":"MIN","363":"MIN","364":"MIN","365":"MIN","366":"MIN","367":"MIN","368":"MIN","369":"MIN","370":"SAC","371":"SAC","372":"SAC","373":"SAC","374":"SAC","375":"SAC","376":"SAC","377":"SAC","378":"SAC","379":"SAC","380":"SAC","381":"SAC","382":"SAC","383":"SAC","384":"SAC","385":"SAC","386":"SAC","387":"SAC","388":"SAC","389":"MIN","390":"SAC","391":"SAC","392":"MIN","393":"MIN","394":"SAC","395":"SAC","396":"MIN","397":"MIN","398":"MIN","399":"SAC","400":"SAC","401":"SAC","402":"SAC","403":"SAC","404":"SAC","405":"SAC","406":"MIN","407":"MIN","408":"SAC","409":"MIN","410":"SAC","411":"MIN","412":"SAC","413":"SAC","414":"MIN","415":"MIN","416":"MIN","417":"MIN","418":"SAC","419":"SAC","420":"SAC","421":"SAC","422":"MIN","423":"MIN","424":"SAC","425":"SAC","426":"SAC","427":"SAC","428":"MIN","429":"SAC","430":"MIN","431":"MIN","432":"SAC","433":"MIN","434":"SAC","435":"SAC","436":"MIN","437":"SAC","438":"MIN","439":"SAC","440":"SAC","441":"MIN","442":"MIN","443":"MIN","444":"MIN","445":"MIN","446":"MIN","447":"SAC","448":"SAC","449":"MIN","450":"MIN","451":"SAC","452":"SAC","453":"SAC","454":"MIN","455":"SAC","456":"SAC","457":"SAC","458":"MIN","459":"MIN","460":"SAC","461":"MIN","462":"MIN","463":"MIN","464":"SAC","465":"SAC","466":"SAC","467":"SAC","468":"MIN","469":"MIN","470":"GSW","471":"GSW","472":"GSW","473":"GSW","474":"GSW","475":"GSW","476":"MEM","477":"GSW","478":"MEM","479":"MEM","480":"MEM","481":"MEM","482":"GSW","483":"MEM","484":"MEM","485":"MEM","486":"MEM","487":"MEM","488":"GSW","489":"GSW","490":"GSW","491":"GSW","492":"GSW","493":"GSW","494":"MEM","495":"GSW","496":"MEM","497":"MEM","498":"MEM","499":"MEM","500":"MEM","501":"GSW","502":"GSW","503":"GSW","504":"MEM","505":"MEM","506":"MEM","507":"MEM","508":"MEM","509":"MEM","510":"MEM","511":"MEM","512":"MEM","513":"MEM","514":"MEM","515":"MEM","516":"MEM","517":"MEM","518":"MEM","519":"MEM","520":"MEM","521":"MEM","522":"MEM","523":"MEM","524":"MEM","525":"GSW","526":"MEM","527":"MEM","528":"GSW","529":"GSW","530":"MEM","531":"MEM","532":"MEM","533":"MEM","534":"MEM","535":"MEM","536":"GSW","537":"MEM","538":"MEM","539":"MEM","540":"GSW","541":"MEM","542":"MEM","543":"MEM","544":"MEM","545":"MEM","546":"MEM","547":"MEM","548":"MEM","549":"MEM","550":"GSW","551":"MEM","552":"MEM","553":"MEM","554":"MEM","555":"GSW","556":"MEM","557":"MEM","558":"GSW","559":"GSW","560":"GSW","561":"GSW","562":"GSW","563":"GSW","564":"GSW","565":"GSW","566":"GSW","567":"MEM","568":"GSW","569":"GSW","570":"MEM","571":"GSW","572":"MEM","573":"GSW","574":"GSW","575":"MEM","576":"MEM","577":"MEM","578":"GSW","579":"MEM","580":"MEM","581":"MEM","582":"GSW","583":"GSW","584":"GSW","585":"MEM","586":"GSW","587":"GSW","588":"GSW","589":"MEM","590":"GSW","591":"MEM","592":"MEM","593":"MEM"},"line_score":{"0":41.5,"1":21.0,"2":5.5,"3":59.0,"4":13.0,"5":53.0,"6":23.5,"7":12.0,"8":49.0,"9":13.0,"10":7.0,"11":27.5,"12":6.0,"13":29.5,"14":36.5,"15":44.5,"16":21.0,"17":8.0,"18":0.5,"19":5.0,"20":20.5,"21":23.5,"22":4.0,"23":32.0,"24":8.0,"25":3.5,"26":16.5,"27":2.5,"28":24.5,"29":28.0,"30":25.0,"31":3.5,"32":21.5,"33":29.5,"34":7.0,"35":23.5,"36":15.5,"37":26.5,"38":10.0,"39":28.5,"40":39.5,"41":3.0,"42":13.5,"43":18.5,"44":6.5,"45":32.5,"46":3.5,"47":22.5,"48":14.5,"49":27.0,"50":14.0,"51":33.5,"52":7.0,"53":11.0,"54":3.5,"55":25.5,"56":9.5,"57":18.5,"58":21.5,"59":0.5,"60":6.0,"61":9.0,"62":32.5,"63":12.5,"64":15.5,"65":6.5,"66":24.5,"67":17.0,"68":9.0,"69":17.5,"70":10.5,"71":14.5,"72":11.5,"73":8.0,"74":14.5,"75":5.0,"76":9.0,"77":3.5,"78":18.5,"79":11.5,"80":10.5,"81":0.5,"82":11.5,"83":1.5,"84":1.5,"85":0.5,"86":0.5,"87":24.5,"88":2.5,"89":20.5,"90":1.5,"91":5.5,"92":0.5,"93":0.5,"94":3.5,"95":17.5,"96":4.5,"97":7.5,"98":2.5,"99":0.5,"100":9.5,"101":18.5,"102":0.5,"103":1.5,"104":8.5,"105":0.5,"106":13.5,"107":5.5,"108":1.5,"109":0.5,"110":0.5,"111":22.5,"112":21.5,"113":0.5,"114":0.5,"115":2.5,"116":29.5,"117":16.5,"118":14.5,"119":30.5,"120":1.5,"121":14.5,"122":1.5,"123":1.5,"124":24.5,"125":5.5,"126":26.5,"127":1.5,"128":0.5,"129":12.5,"130":4.5,"131":3.5,"132":7.5,"133":3.5,"134":3.5,"135":0.5,"136":1.5,"137":26.5,"138":7.5,"139":3.5,"140":14.5,"141":4.5,"142":6.5,"143":2.5,"144":17.5,"145":19.5,"146":11.5,"147":1.5,"148":0.5,"149":7.5,"150":14.5,"151":36.5,"152":4.0,"153":27.0,"154":29.0,"155":11.0,"156":22.5,"157":6.5,"158":34.0,"159":14.5,"160":20.5,"161":18.5,"162":24.5,"163":29.5,"164":9.5,"165":20.0,"166":27.0,"167":37.0,"168":6.5,"169":24.5,"170":30.5,"171":12.0,"172":31.5,"173":5.5,"174":5.5,"175":19.5,"176":21.0,"177":23.5,"178":18.5,"179":16.5,"180":18.5,"181":12.5,"182":6.0,"183":17.5,"184":23.5,"185":11.0,"186":17.5,"187":15.5,"188":7.0,"189":19.5,"190":17.5,"191":12.5,"192":5.5,"193":3.5,"194":13.5,"195":19.5,"196":27.5,"197":7.5,"198":3.5,"199":39.5,"200":2.5,"201":0.5,"202":1.5,"203":1.5,"204":3.5,"205":1.5,"206":5.5,"207":19.5,"208":3.5,"209":17.5,"210":38.5,"211":6.0,"212":34.0,"213":32.0,"214":10.5,"215":27.5,"216":37.5,"217":31.5,"218":6.0,"219":43.5,"220":37.5,"221":22.5,"222":9.5,"223":6.5,"224":19.5,"225":12.5,"226":15.5,"227":21.5,"228":6.5,"229":28.5,"230":27.5,"231":34.0,"232":12.0,"233":10.5,"234":23.0,"235":25.5,"236":13.5,"237":11.5,"238":17.0,"239":18.5,"240":14.5,"241":11.5,"242":8.5,"243":7.5,"244":42.5,"245":3.5,"246":0.5,"247":0.5,"248":0.5,"249":1.5,"250":0.5,"251":9.5,"252":4.5,"253":5.5,"254":0.5,"255":10.5,"256":20.5,"257":32.5,"258":17.5,"259":4.5,"260":36.5,"261":24.5,"262":4.5,"263":0.5,"264":7.5,"265":5.5,"266":8.5,"267":8.5,"268":33.5,"269":46.5,"270":7.5,"271":0.5,"272":3.5,"273":14.5,"274":2.5,"275":3.5,"276":14.5,"277":2.5,"278":2.5,"279":24.5,"280":1.5,"281":7.5,"282":5.5,"283":3.5,"284":13.5,"285":13.5,"286":1.5,"287":1.5,"288":0.5,"289":32.5,"290":7.5,"291":37.5,"292":4.5,"293":31.5,"294":32.5,"295":21.0,"296":10.5,"297":27.0,"298":41.5,"299":4.5,"300":5.5,"301":3.5,"302":10.0,"303":32.0,"304":0.5,"305":6.0,"306":10.5,"307":43.5,"308":4.5,"309":31.0,"310":21.5,"311":37.0,"312":25.5,"313":5.5,"314":4.5,"315":25.0,"316":36.5,"317":4.5,"318":33.0,"319":5.5,"320":7.5,"321":12.5,"322":5.0,"323":15.0,"324":28.0,"325":4.0,"326":3.5,"327":12.0,"328":19.5,"329":13.5,"330":9.5,"331":31.5,"332":19.5,"333":39.5,"334":46.0,"335":3.0,"336":26.5,"337":11.5,"338":6.0,"339":3.5,"340":2.5,"341":31.0,"342":10.5,"343":22.5,"344":8.0,"345":15.5,"346":1.5,"347":12.5,"348":6.5,"349":29.5,"350":5.0,"351":22.5,"352":7.0,"353":14.5,"354":20.5,"355":8.5,"356":10.5,"357":0.5,"358":1.5,"359":4.0,"360":7.5,"361":28.5,"362":17.0,"363":4.0,"364":2.5,"365":0.5,"366":21.5,"367":7.0,"368":12.0,"369":18.5,"370":4.5,"371":21.5,"372":14.5,"373":7.0,"374":13.5,"375":16.5,"376":13.5,"377":10.5,"378":18.5,"379":0.5,"380":5.5,"381":13.0,"382":20.5,"383":10.5,"384":9.5,"385":1.5,"386":7.5,"387":3.5,"388":3.5,"389":19.5,"390":2.5,"391":24.5,"392":5.5,"393":4.5,"394":0.5,"395":3.5,"396":1.5,"397":3.5,"398":24.5,"399":4.5,"400":29.5,"401":34.5,"402":3.5,"403":14.5,"404":14.5,"405":13.5,"406":1.5,"407":5.5,"408":1.5,"409":4.5,"410":5.5,"411":1.5,"412":2.5,"413":14.5,"414":3.5,"415":19.5,"416":24.5,"417":15.5,"418":1.5,"419":5.5,"420":24.5,"421":19.5,"422":19.5,"423":3.5,"424":9.5,"425":5.5,"426":1.5,"427":2.5,"428":9.5,"429":26.5,"430":21.5,"431":0.5,"432":14.5,"433":13.5,"434":1.5,"435":4.5,"436":14.5,"437":7.5,"438":1.5,"439":13.5,"440":1.5,"441":2.5,"442":9.5,"443":0.5,"444":7.5,"445":29.5,"446":5.5,"447":5.5,"448":1.5,"449":1.5,"450":2.5,"451":0.5,"452":9.5,"453":9.5,"454":9.5,"455":14.5,"456":15.5,"457":0.5,"458":2.5,"459":14.5,"460":5.5,"461":0.5,"462":1.5,"463":9.5,"464":0.5,"465":0.5,"466":3.5,"467":0.5,"468":5.5,"469":0.5,"470":6.0,"471":21.5,"472":36.5,"473":18.0,"474":4.5,"475":5.5,"476":37.5,"477":27.5,"478":12.0,"479":31.5,"480":6.0,"481":4.5,"482":22.5,"483":3.5,"484":33.5,"485":27.0,"486":42.5,"487":19.5,"488":18.5,"489":11.5,"490":11.5,"491":5.0,"492":7.0,"493":28.5,"494":21.0,"495":1.5,"496":20.0,"497":27.5,"498":4.5,"499":5.0,"500":12.5,"501":6.5,"502":9.0,"503":16.0,"504":8.5,"505":15.0,"506":28.5,"507":5.5,"508":11.0,"509":6.5,"510":4.0,"511":17.5,"512":5.0,"513":21.5,"514":16.5,"515":18.5,"516":23.5,"517":18.5,"518":15.5,"519":16.0,"520":0.5,"521":7.5,"522":14.5,"523":2.5,"524":14.5,"525":0.5,"526":19.5,"527":3.5,"528":2.5,"529":9.5,"530":0.5,"531":3.5,"532":35.5,"533":24.5,"534":4.5,"535":2.5,"536":1.5,"537":9.5,"538":0.5,"539":17.5,"540":2.5,"541":1.5,"542":6.5,"543":5.5,"544":1.5,"545":0.5,"546":0.5,"547":19.5,"548":1.5,"549":24.5,"550":1.5,"551":9.5,"552":5.5,"553":3.5,"554":0.5,"555":0.5,"556":13.5,"557":4.5,"558":2.5,"559":2.5,"560":2.5,"561":17.5,"562":14.5,"563":0.5,"564":0.5,"565":1.5,"566":19.5,"567":9.5,"568":9.5,"569":14.5,"570":5.5,"571":29.5,"572":6.5,"573":1.5,"574":4.5,"575":1.5,"576":5.5,"577":8.5,"578":7.5,"579":7.5,"580":29.5,"581":41.5,"582":4.5,"583":9.5,"584":1.5,"585":20.5,"586":14.5,"587":0.5,"588":1.5,"589":0.5,"590":4.5,"591":5.5,"592":0.5,"593":17.5},"stat_type":{"0":"Points (Combo)","1":"Rebounds (Combo)","2":"3-PT Made (Combo)","3":"Points (Combo)","4":"Assists (Combo)","5":"Points (Combo)","6":"Rebounds (Combo)","7":"Assists (Combo)","8":"Points (Combo)","9":"Rebounds (Combo)","10":"3-PT Made (Combo)","11":"Pts+Rebs","12":"Rebounds","13":"Pts+Asts","14":"Pts+Rebs+Asts","15":"Fantasy Score","16":"Points","17":"Assists","18":"Offensive Rebounds","19":"Free Throws Made","20":"Points","21":"Pts+Asts","22":"Rebounds","23":"Fantasy Score","24":"3-PT Attempted","25":"Free Throws Made","26":"FG Attempted","27":"3-PT Made","28":"Pts+Rebs","29":"Pts+Rebs+Asts","30":"Pts+Rebs","31":"Free Throws Made","32":"Points","33":"Fantasy Score","34":"3-PT Attempted","35":"Pts+Asts","36":"FG Attempted","37":"Pts+Rebs+Asts","38":"Rebounds","39":"Pts+Rebs","40":"Fantasy Score","41":"Free Throws Made","42":"FG Attempted","43":"Points","44":"Defensive Rebounds","45":"Pts+Rebs+Asts","46":"Offensive Rebounds","47":"Pts+Asts","48":"Rebs+Asts","49":"Pts+Rebs+Asts","50":"Points","51":"Fantasy Score","52":"Defensive Rebounds","53":"Rebounds","54":"Offensive Rebounds","55":"Pts+Rebs","56":"FG Attempted","57":"Pts+Rebs","58":"Pts+Asts","59":"Offensive Rebounds","60":"Assists","61":"Rebs+Asts","62":"Fantasy Score","63":"FG Attempted","64":"Points","65":"3-PT Attempted","66":"Pts+Rebs+Asts","67":"Fantasy Score","68":"Points","69":"Fantasy Score","70":"Points","71":"Pts+Rebs+Asts","72":"Pts+Asts","73":"FG Attempted","74":"Pts+Rebs","75":"Rebounds","76":"Points","77":"3-PT Attempted","78":"Fantasy Score","79":"Points","80":"Points","81":"Blocked Shots","82":"Rebounds","83":"Blocked Shots","84":"Steals","85":"3-PT Made","86":"3-PT Made","87":"Points","88":"3-PT Made","89":"Points","90":"Turnovers","91":"Assists","92":"Blocked Shots","93":"Assists","94":"Rebounds","95":"Points","96":"Assists","97":"Points","98":"Assists","99":"Assists","100":"Points","101":"Points","102":"Steals","103":"3-PT Made","104":"Points","105":"3-PT Made","106":"Points","107":"Points","108":"3-PT Made","109":"Steals","110":"3-PT Made","111":"Pts+Rebs+Asts","112":"Pts+Rebs+Asts","113":"Steals","114":"Blocked Shots","115":"Assists","116":"Pts+Rebs+Asts","117":"Points","118":"Points","119":"Pts+Rebs+Asts","120":"Turnovers","121":"Points","122":"3-PT Made","123":"Steals","124":"Points","125":"Rebounds","126":"Points","127":"Steals","128":"Blocked Shots","129":"Points","130":"Rebounds","131":"Rebounds","132":"Assists","133":"Rebounds","134":"3-PT Made","135":"Blocked Shots","136":"3-PT Made","137":"Pts+Rebs+Asts","138":"Rebounds","139":"3-PT Made","140":"Points","141":"Assists","142":"Assists","143":"Steals","144":"Points","145":"Points","146":"Points","147":"Assists","148":"Blocked Shots","149":"Rebounds","150":"Points","151":"Pts+Rebs+Asts","152":"Rebounds","153":"Pts+Rebs","154":"Pts+Asts","155":"Rebs+Asts","156":"Points","157":"Assists","158":"Pts+Rebs+Asts","159":"Points","160":"Pts+Rebs","161":"Pts+Asts","162":"Pts+Rebs+Asts","163":"Pts+Rebs+Asts","164":"Rebs+Asts","165":"Points","166":"Pts+Rebs","167":"Pts+Rebs+Asts","168":"Assists","169":"Points","170":"Pts+Rebs","171":"Rebs+Asts","172":"Pts+Asts","173":"Rebounds","174":"Rebounds","175":"Pts+Rebs","176":"Pts+Rebs","177":"Pts+Rebs+Asts","178":"Pts+Asts","179":"Points","180":"Pts+Asts","181":"Points","182":"Assists","183":"Pts+Rebs","184":"Pts+Rebs+Asts","185":"Rebs+Asts","186":"Pts+Rebs+Asts","187":"Pts+Rebs","188":"Rebounds","189":"Pts+Rebs+Asts","190":"Pts+Rebs","191":"Points","192":"Rebounds","193":"3-PT Made","194":"Points","195":"Pts+Rebs+Asts","196":"Points","197":"Assists","198":"3-PT Made","199":"Pts+Rebs+Asts","200":"3-PT Made","201":"3-PT Made","202":"3-PT Made","203":"3-PT Made","204":"Rebounds","205":"Assists","206":"Assists","207":"Points","208":"Assists","209":"Points","210":"Pts+Rebs+Asts","211":"Assists","212":"Pts+Asts","213":"Pts+Rebs","214":"Rebs+Asts","215":"Points","216":"Pts+Asts","217":"Points","218":"Rebounds","219":"Pts+Rebs+Asts","220":"Pts+Rebs","221":"Pts+Rebs+Asts","222":"Rebs+Asts","223":"Assists","224":"Pts+Asts","225":"Points","226":"Pts+Rebs","227":"Points","228":"Rebounds","229":"Pts+Rebs","230":"Pts+Asts","231":"Pts+Rebs+Asts","232":"Rebounds","233":"Points","234":"Pts+Rebs","235":"Pts+Rebs+Asts","236":"Pts+Asts","237":"Points","238":"Pts+Rebs","239":"Pts+Rebs+Asts","240":"Pts+Asts","241":"Points","242":"Points","243":"Assists","244":"Pts+Rebs+Asts","245":"Rebounds","246":"Turnovers","247":"Steals","248":"Steals","249":"3-PT Made","250":"Blocked Shots","251":"Points","252":"Assists","253":"Assists","254":"Steals","255":"Points","256":"Pts+Rebs+Asts","257":"Pts+Rebs+Asts","258":"Points","259":"Assists","260":"Pts+Rebs+Asts","261":"Points","262":"Assists","263":"Steals","264":"Points","265":"Rebounds","266":"Rebounds","267":"Assists","268":"Points","269":"Pts+Rebs+Asts","270":"Rebounds","271":"Blocked Shots","272":"Rebounds","273":"Points","274":"3-PT Made","275":"3-PT Made","276":"Points","277":"3-PT Made","278":"3-PT Made","279":"Points","280":"Blocked Shots","281":"Rebounds","282":"Rebounds","283":"3-PT Made","284":"Rebounds","285":"Points","286":"Steals","287":"Blocked Shots","288":"Blocked Shots","289":"Points","290":"Assists","291":"Pts+Rebs+Asts","292":"Free Throws Made","293":"Pts+Asts","294":"Pts+Rebs","295":"FG Attempted","296":"Rebs+Asts","297":"Points","298":"Fantasy Score","299":"Assists","300":"Rebounds","301":"3-PT Made","302":"3-PT Attempted","303":"Pts+Asts","304":"Offensive Rebounds","305":"3-PT Attempted","306":"Rebs+Asts","307":"Fantasy Score","308":"Free Throws Made","309":"Pts+Rebs","310":"FG Attempted","311":"Pts+Rebs+Asts","312":"Points","313":"Assists","314":"Rebounds","315":"Pts+Asts","316":"Fantasy Score","317":"Assists","318":"Pts+Rebs+Asts","319":"Defensive Rebounds","320":"Rebounds","321":"Rebs+Asts","322":"3-PT Attempted","323":"FG Attempted","324":"Pts+Rebs","325":"Free Throws Made","326":"Free Throws Made","327":"Rebounds","328":"Points","329":"FG Attempted","330":"Defensive Rebounds","331":"Pts+Rebs","332":"Rebs+Asts","333":"Pts+Rebs+Asts","334":"Fantasy Score","335":"Offensive Rebounds","336":"Pts+Asts","337":"Rebounds","338":"FG Attempted","339":"Offensive Rebounds","340":"Free Throws Made","341":"Fantasy Score","342":"Points","343":"Pts+Rebs","344":"Defensive Rebounds","345":"Points","346":"Free Throws Made","347":"FG Attempted","348":"3-PT Attempted","349":"Fantasy Score","350":"Defensive Rebounds","351":"Pts+Rebs","352":"Rebounds","353":"Pts+Rebs","354":"Fantasy Score","355":"FG Attempted","356":"Points","357":"Free Throws Made","358":"Blks+Stls","359":"Rebounds","360":"Rebs+Asts","361":"Fantasy Score","362":"Pts+Asts","363":"Rebounds","364":"3-PT Made","365":"Free Throws Made","366":"Pts+Rebs+Asts","367":"3-PT Attempted","368":"FG Attempted","369":"Pts+Rebs","370":"3-PT Attempted","371":"Fantasy Score","372":"Pts+Asts","373":"FG Attempted","374":"Pts+Rebs","375":"Pts+Rebs+Asts","376":"Pts+Asts","377":"Points","378":"Pts+Rebs","379":"Steals","380":"Rebounds","381":"Points","382":"Pts+Rebs+Asts","383":"Pts+Asts","384":"Pts+Rebs","385":"3-PT Made","386":"Points","387":"Assists","388":"Rebounds","389":"Pts+Rebs+Asts","390":"3-PT Made","391":"Points","392":"Assists","393":"Assists","394":"Steals","395":"Assists","396":"3-PT Made","397":"Rebounds","398":"Points","399":"Rebounds","400":"Points","401":"Points","402":"Rebounds","403":"Rebounds","404":"Points","405":"Rebounds","406":"Turnovers","407":"Rebounds","408":"Blocked Shots","409":"Assists","410":"Assists","411":"Turnovers","412":"3-PT Made","413":"Points","414":"3-PT Made","415":"Points","416":"Points","417":"Rebounds","418":"Assists","419":"Rebounds","420":"Points","421":"Pts+Rebs+Asts","422":"Points","423":"3-PT Made","424":"Rebounds","425":"Assists","426":"Steals","427":"3-PT Made","428":"Rebounds","429":"Points","430":"Points","431":"Blocked Shots","432":"Points","433":"Rebounds","434":"Turnovers","435":"3-PT Made","436":"Rebounds","437":"Rebounds","438":"3-PT Made","439":"Pts+Rebs+Asts","440":"3-PT Made","441":"Steals","442":"Assists","443":"Blocked Shots","444":"Assists","445":"Points","446":"Rebounds","447":"Assists","448":"Steals","449":"3-PT Made","450":"3-PT Made","451":"Blocked Shots","452":"Rebounds","453":"Points","454":"Rebounds","455":"Points","456":"Pts+Rebs+Asts","457":"Steals","458":"Assists","459":"Points","460":"Points","461":"Steals","462":"3-PT Made","463":"Points","464":"Steals","465":"Blocked Shots","466":"Assists","467":"3-PT Made","468":"Rebounds","469":"Steals","470":"3-PT Attempted","471":"Points","472":"Fantasy Score","473":"FG Attempted","474":"Free Throws Made","475":"Rebounds","476":"Pts+Rebs+Asts","477":"Pts+Rebs","478":"3-PT Attempted","479":"Pts+Rebs","480":"Assists","481":"Rebounds","482":"Pts+Rebs+Asts","483":"Free Throws Made","484":"Pts+Asts","485":"Points","486":"Fantasy Score","487":"FG Attempted","488":"Pts+Rebs","489":"Points","490":"FG Attempted","491":"3-PT Attempted","492":"Rebounds","493":"Fantasy Score","494":"Pts+Rebs+Asts","495":"3-PT Made","496":"Pts+Rebs","497":"Fantasy Score","498":"Rebounds","499":"3-PT Attempted","500":"FG Attempted","501":"Rebounds","502":"Points","503":"Pts+Rebs","504":"Points","505":"Pts+Rebs","506":"Fantasy Score","507":"Assists","508":"Pts+Rebs","509":"Points","510":"Rebounds","511":"Fantasy Score","512":"Rebounds","513":"Pts+Rebs","514":"Points","515":"Pts+Asts","516":"Pts+Rebs+Asts","517":"Pts+Rebs+Asts","518":"Pts+Asts","519":"Pts+Rebs","520":"Steals","521":"Rebounds","522":"Points","523":"3-PT Made","524":"Points","525":"Steals","526":"Pts+Rebs+Asts","527":"Rebounds","528":"Assists","529":"Points","530":"Steals","531":"3-PT Made","532":"Pts+Rebs+Asts","533":"Points","534":"Assists","535":"Assists","536":"Blocked Shots","537":"Points","538":"3-PT Made","539":"Points","540":"3-PT Made","541":"Steals","542":"Assists","543":"Rebounds","544":"Blocked Shots","545":"Blocked Shots","546":"Blocked Shots","547":"Points","548":"3-PT Made","549":"Pts+Rebs+Asts","550":"Assists","551":"Points","552":"Points","553":"Rebounds","554":"Steals","555":"Steals","556":"Points","557":"Assists","558":"3-PT Made","559":"Rebounds","560":"3-PT Made","561":"Points","562":"Points","563":"Blocked Shots","564":"Blocked Shots","565":"3-PT Made","566":"Points","567":"Points","568":"Rebounds","569":"Points","570":"Rebounds","571":"Points","572":"3-PT Made","573":"Steals","574":"Rebounds","575":"Steals","576":"Rebounds","577":"Points","578":"Rebounds","579":"Assists","580":"Points","581":"Pts+Rebs+Asts","582":"Assists","583":"Rebounds","584":"Blocked Shots","585":"Pts+Rebs+Asts","586":"Points","587":"3-PT Made","588":"Assists","589":"3-PT Made","590":"Rebounds","591":"Points","592":"3-PT Made","593":"Pts+Rebs+Asts"},"start_time":{"0":"2024-11-15T20:10:00-05:00","1":"2024-11-15T20:10:00-05:00","2":"2024-11-15T20:10:00-05:00","3":"2024-11-15T20:10:00-05:00","4":"2024-11-15T20:10:00-05:00","5":"2024-11-15T20:10:00-05:00","6":"2024-11-15T22:10:00-05:00","7":"2024-11-15T22:10:00-05:00","8":"2024-11-15T22:10:00-05:00","9":"2024-11-15T22:10:00-05:00","10":"2024-11-15T22:10:00-05:00","11":"2024-11-15T20:10:00-05:00","12":"2024-11-15T20:10:00-05:00","13":"2024-11-15T20:10:00-05:00","14":"2024-11-15T20:10:00-05:00","15":"2024-11-15T20:10:00-05:00","16":"2024-11-15T20:10:00-05:00","17":"2024-11-15T20:10:00-05:00","18":"2024-11-15T20:10:00-05:00","19":"2024-11-15T20:10:00-05:00","20":"2024-11-15T20:10:00-05:00","21":"2024-11-15T20:10:00-05:00","22":"2024-11-15T20:10:00-05:00","23":"2024-11-15T20:10:00-05:00","24":"2024-11-15T20:10:00-05:00","25":"2024-11-15T20:10:00-05:00","26":"2024-11-15T20:10:00-05:00","27":"2024-11-15T20:10:00-05:00","28":"2024-11-15T20:10:00-05:00","29":"2024-11-15T20:10:00-05:00","30":"2024-11-15T20:10:00-05:00","31":"2024-11-15T20:10:00-05:00","32":"2024-11-15T20:10:00-05:00","33":"2024-11-15T20:10:00-05:00","34":"2024-11-15T20:10:00-05:00","35":"2024-11-15T20:10:00-05:00","36":"2024-11-15T20:10:00-05:00","37":"2024-11-15T20:10:00-05:00","38":"2024-11-15T20:10:00-05:00","39":"2024-11-15T20:10:00-05:00","40":"2024-11-15T20:10:00-05:00","41":"2024-11-15T20:10:00-05:00","42":"2024-11-15T20:10:00-05:00","43":"2024-11-15T20:10:00-05:00","44":"2024-11-15T20:10:00-05:00","45":"2024-11-15T20:10:00-05:00","46":"2024-11-15T20:10:00-05:00","47":"2024-11-15T20:10:00-05:00","48":"2024-11-15T20:10:00-05:00","49":"2024-11-15T20:10:00-05:00","50":"2024-11-15T20:10:00-05:00","51":"2024-11-15T20:10:00-05:00","52":"2024-11-15T20:10:00-05:00","53":"2024-11-15T20:10:00-05:00","54":"2024-11-15T20:10:00-05:00","55":"2024-11-15T20:10:00-05:00","56":"2024-11-15T20:10:00-05:00","57":"2024-11-15T20:10:00-05:00","58":"2024-11-15T20:10:00-05:00","59":"2024-11-15T20:10:00-05:00","60":"2024-11-15T20:10:00-05:00","61":"2024-11-15T20:10:00-05:00","62":"2024-11-15T20:10:00-05:00","63":"2024-11-15T20:10:00-05:00","64":"2024-11-15T20:10:00-05:00","65":"2024-11-15T20:10:00-05:00","66":"2024-11-15T20:10:00-05:00","67":"2024-11-15T20:10:00-05:00","68":"2024-11-15T20:10:00-05:00","69":"2024-11-15T20:10:00-05:00","70":"2024-11-15T20:10:00-05:00","71":"2024-11-15T20:10:00-05:00","72":"2024-11-15T20:10:00-05:00","73":"2024-11-15T20:10:00-05:00","74":"2024-11-15T20:10:00-05:00","75":"2024-11-15T20:10:00-05:00","76":"2024-11-15T20:10:00-05:00","77":"2024-11-15T20:10:00-05:00","78":"2024-11-15T20:10:00-05:00","79":"2024-11-15T20:10:00-05:00","80":"2024-11-15T20:10:00-05:00","81":"2024-11-15T20:10:00-05:00","82":"2024-11-15T20:10:00-05:00","83":"2024-11-15T20:10:00-05:00","84":"2024-11-15T20:10:00-05:00","85":"2024-11-15T20:10:00-05:00","86":"2024-11-15T20:10:00-05:00","87":"2024-11-15T20:10:00-05:00","88":"2024-11-15T20:10:00-05:00","89":"2024-11-15T20:10:00-05:00","90":"2024-11-15T20:10:00-05:00","91":"2024-11-15T20:10:00-05:00","92":"2024-11-15T20:10:00-05:00","93":"2024-11-15T20:10:00-05:00","94":"2024-11-15T20:10:00-05:00","95":"2024-11-15T20:10:00-05:00","96":"2024-11-15T20:10:00-05:00","97":"2024-11-15T20:10:00-05:00","98":"2024-11-15T20:10:00-05:00","99":"2024-11-15T20:10:00-05:00","100":"2024-11-15T20:10:00-05:00","101":"2024-11-15T20:10:00-05:00","102":"2024-11-15T20:10:00-05:00","103":"2024-11-15T20:10:00-05:00","104":"2024-11-15T20:10:00-05:00","105":"2024-11-15T20:10:00-05:00","106":"2024-11-15T20:10:00-05:00","107":"2024-11-15T20:10:00-05:00","108":"2024-11-15T20:10:00-05:00","109":"2024-11-15T20:10:00-05:00","110":"2024-11-15T20:10:00-05:00","111":"2024-11-15T20:10:00-05:00","112":"2024-11-15T20:10:00-05:00","113":"2024-11-15T20:10:00-05:00","114":"2024-11-15T20:10:00-05:00","115":"2024-11-15T20:10:00-05:00","116":"2024-11-15T20:10:00-05:00","117":"2024-11-15T20:10:00-05:00","118":"2024-11-15T20:10:00-05:00","119":"2024-11-15T20:10:00-05:00","120":"2024-11-15T20:10:00-05:00","121":"2024-11-15T20:10:00-05:00","122":"2024-11-15T20:10:00-05:00","123":"2024-11-15T20:10:00-05:00","124":"2024-11-15T20:10:00-05:00","125":"2024-11-15T20:10:00-05:00","126":"2024-11-15T20:10:00-05:00","127":"2024-11-15T20:10:00-05:00","128":"2024-11-15T20:10:00-05:00","129":"2024-11-15T20:10:00-05:00","130":"2024-11-15T20:10:00-05:00","131":"2024-11-15T20:10:00-05:00","132":"2024-11-15T20:10:00-05:00","133":"2024-11-15T20:10:00-05:00","134":"2024-11-15T20:10:00-05:00","135":"2024-11-15T20:10:00-05:00","136":"2024-11-15T20:10:00-05:00","137":"2024-11-15T20:10:00-05:00","138":"2024-11-15T20:10:00-05:00","139":"2024-11-15T20:10:00-05:00","140":"2024-11-15T20:10:00-05:00","141":"2024-11-15T20:10:00-05:00","142":"2024-11-15T20:10:00-05:00","143":"2024-11-15T20:10:00-05:00","144":"2024-11-15T20:10:00-05:00","145":"2024-11-15T20:10:00-05:00","146":"2024-11-15T20:10:00-05:00","147":"2024-11-15T20:10:00-05:00","148":"2024-11-15T20:10:00-05:00","149":"2024-11-15T20:10:00-05:00","150":"2024-11-15T20:10:00-05:00","151":"2024-11-15T20:10:00-05:00","152":"2024-11-15T20:10:00-05:00","153":"2024-11-15T20:10:00-05:00","154":"2024-11-15T20:10:00-05:00","155":"2024-11-15T20:10:00-05:00","156":"2024-11-15T20:10:00-05:00","157":"2024-11-15T20:10:00-05:00","158":"2024-11-15T20:10:00-05:00","159":"2024-11-15T20:10:00-05:00","160":"2024-11-15T20:10:00-05:00","161":"2024-11-15T20:10:00-05:00","162":"2024-11-15T20:10:00-05:00","163":"2024-11-15T20:10:00-05:00","164":"2024-11-15T20:10:00-05:00","165":"2024-11-15T20:10:00-05:00","166":"2024-11-15T20:10:00-05:00","167":"2024-11-15T20:10:00-05:00","168":"2024-11-15T20:10:00-05:00","169":"2024-11-15T20:10:00-05:00","170":"2024-11-15T20:10:00-05:00","171":"2024-11-15T20:10:00-05:00","172":"2024-11-15T20:10:00-05:00","173":"2024-11-15T20:10:00-05:00","174":"2024-11-15T20:10:00-05:00","175":"2024-11-15T20:10:00-05:00","176":"2024-11-15T20:10:00-05:00","177":"2024-11-15T20:10:00-05:00","178":"2024-11-15T20:10:00-05:00","179":"2024-11-15T20:10:00-05:00","180":"2024-11-15T20:10:00-05:00","181":"2024-11-15T20:10:00-05:00","182":"2024-11-15T20:10:00-05:00","183":"2024-11-15T20:10:00-05:00","184":"2024-11-15T20:10:00-05:00","185":"2024-11-15T20:10:00-05:00","186":"2024-11-15T20:10:00-05:00","187":"2024-11-15T20:10:00-05:00","188":"2024-11-15T20:10:00-05:00","189":"2024-11-15T20:10:00-05:00","190":"2024-11-15T20:10:00-05:00","191":"2024-11-15T20:10:00-05:00","192":"2024-11-15T20:10:00-05:00","193":"2024-11-15T20:10:00-05:00","194":"2024-11-15T20:10:00-05:00","195":"2024-11-15T20:10:00-05:00","196":"2024-11-15T20:10:00-05:00","197":"2024-11-15T20:10:00-05:00","198":"2024-11-15T20:10:00-05:00","199":"2024-11-15T20:10:00-05:00","200":"2024-11-15T20:10:00-05:00","201":"2024-11-15T20:10:00-05:00","202":"2024-11-15T20:10:00-05:00","203":"2024-11-15T20:10:00-05:00","204":"2024-11-15T20:10:00-05:00","205":"2024-11-15T20:10:00-05:00","206":"2024-11-15T20:10:00-05:00","207":"2024-11-15T20:10:00-05:00","208":"2024-11-15T20:10:00-05:00","209":"2024-11-15T20:10:00-05:00","210":"2024-11-15T20:10:00-05:00","211":"2024-11-15T20:10:00-05:00","212":"2024-11-15T20:10:00-05:00","213":"2024-11-15T20:10:00-05:00","214":"2024-11-15T20:10:00-05:00","215":"2024-11-15T20:10:00-05:00","216":"2024-11-15T20:10:00-05:00","217":"2024-11-15T20:10:00-05:00","218":"2024-11-15T20:10:00-05:00","219":"2024-11-15T20:10:00-05:00","220":"2024-11-15T20:10:00-05:00","221":"2024-11-15T20:10:00-05:00","222":"2024-11-15T20:10:00-05:00","223":"2024-11-15T20:10:00-05:00","224":"2024-11-15T20:10:00-05:00","225":"2024-11-15T20:10:00-05:00","226":"2024-11-15T20:10:00-05:00","227":"2024-11-15T20:10:00-05:00","228":"2024-11-15T20:10:00-05:00","229":"2024-11-15T20:10:00-05:00","230":"2024-11-15T20:10:00-05:00","231":"2024-11-15T20:10:00-05:00","232":"2024-11-15T20:10:00-05:00","233":"2024-11-15T20:10:00-05:00","234":"2024-11-15T20:10:00-05:00","235":"2024-11-15T20:10:00-05:00","236":"2024-11-15T20:10:00-05:00","237":"2024-11-15T20:10:00-05:00","238":"2024-11-15T20:10:00-05:00","239":"2024-11-15T20:10:00-05:00","240":"2024-11-15T20:10:00-05:00","241":"2024-11-15T20:10:00-05:00","242":"2024-11-15T20:10:00-05:00","243":"2024-11-15T20:10:00-05:00","244":"2024-11-15T20:10:00-05:00","245":"2024-11-15T20:10:00-05:00","246":"2024-11-15T20:10:00-05:00","247":"2024-11-15T20:10:00-05:00","248":"2024-11-15T20:10:00-05:00","249":"2024-11-15T20:10:00-05:00","250":"2024-11-15T20:10:00-05:00","251":"2024-11-15T20:10:00-05:00","252":"2024-11-15T20:10:00-05:00","253":"2024-11-15T20:10:00-05:00","254":"2024-11-15T20:10:00-05:00","255":"2024-11-15T20:10:00-05:00","256":"2024-11-15T20:10:00-05:00","257":"2024-11-15T20:10:00-05:00","258":"2024-11-15T20:10:00-05:00","259":"2024-11-15T20:10:00-05:00","260":"2024-11-15T20:10:00-05:00","261":"2024-11-15T20:10:00-05:00","262":"2024-11-15T20:10:00-05:00","263":"2024-11-15T20:10:00-05:00","264":"2024-11-15T20:10:00-05:00","265":"2024-11-15T20:10:00-05:00","266":"2024-11-15T20:10:00-05:00","267":"2024-11-15T20:10:00-05:00","268":"2024-11-15T20:10:00-05:00","269":"2024-11-15T20:10:00-05:00","270":"2024-11-15T20:10:00-05:00","271":"2024-11-15T20:10:00-05:00","272":"2024-11-15T20:10:00-05:00","273":"2024-11-15T20:10:00-05:00","274":"2024-11-15T20:10:00-05:00","275":"2024-11-15T20:10:00-05:00","276":"2024-11-15T20:10:00-05:00","277":"2024-11-15T20:10:00-05:00","278":"2024-11-15T20:10:00-05:00","279":"2024-11-15T20:10:00-05:00","280":"2024-11-15T20:10:00-05:00","281":"2024-11-15T20:10:00-05:00","282":"2024-11-15T20:10:00-05:00","283":"2024-11-15T20:10:00-05:00","284":"2024-11-15T20:10:00-05:00","285":"2024-11-15T20:10:00-05:00","286":"2024-11-15T20:10:00-05:00","287":"2024-11-15T20:10:00-05:00","288":"2024-11-15T20:10:00-05:00","289":"2024-11-15T20:10:00-05:00","290":"2024-11-15T20:10:00-05:00","291":"2024-11-15T22:10:00-05:00","292":"2024-11-15T22:10:00-05:00","293":"2024-11-15T22:10:00-05:00","294":"2024-11-15T22:10:00-05:00","295":"2024-11-15T22:10:00-05:00","296":"2024-11-15T22:10:00-05:00","297":"2024-11-15T22:10:00-05:00","298":"2024-11-15T22:10:00-05:00","299":"2024-11-15T22:10:00-05:00","300":"2024-11-15T22:10:00-05:00","301":"2024-11-15T22:10:00-05:00","302":"2024-11-15T22:10:00-05:00","303":"2024-11-15T22:10:00-05:00","304":"2024-11-15T22:10:00-05:00","305":"2024-11-15T22:10:00-05:00","306":"2024-11-15T22:10:00-05:00","307":"2024-11-15T22:10:00-05:00","308":"2024-11-15T22:10:00-05:00","309":"2024-11-15T22:10:00-05:00","310":"2024-11-15T22:10:00-05:00","311":"2024-11-15T22:10:00-05:00","312":"2024-11-15T22:10:00-05:00","313":"2024-11-15T22:10:00-05:00","314":"2024-11-15T22:10:00-05:00","315":"2024-11-15T22:10:00-05:00","316":"2024-11-15T22:10:00-05:00","317":"2024-11-15T22:10:00-05:00","318":"2024-11-15T22:10:00-05:00","319":"2024-11-15T22:10:00-05:00","320":"2024-11-15T22:10:00-05:00","321":"2024-11-15T22:10:00-05:00","322":"2024-11-15T22:10:00-05:00","323":"2024-11-15T22:10:00-05:00","324":"2024-11-15T22:10:00-05:00","325":"2024-11-15T22:10:00-05:00","326":"2024-11-15T22:10:00-05:00","327":"2024-11-15T22:10:00-05:00","328":"2024-11-15T22:10:00-05:00","329":"2024-11-15T22:10:00-05:00","330":"2024-11-15T22:10:00-05:00","331":"2024-11-15T22:10:00-05:00","332":"2024-11-15T22:10:00-05:00","333":"2024-11-15T22:10:00-05:00","334":"2024-11-15T22:10:00-05:00","335":"2024-11-15T22:10:00-05:00","336":"2024-11-15T22:10:00-05:00","337":"2024-11-15T22:10:00-05:00","338":"2024-11-15T22:10:00-05:00","339":"2024-11-15T22:10:00-05:00","340":"2024-11-15T22:10:00-05:00","341":"2024-11-15T22:10:00-05:00","342":"2024-11-15T22:10:00-05:00","343":"2024-11-15T22:10:00-05:00","344":"2024-11-15T22:10:00-05:00","345":"2024-11-15T22:10:00-05:00","346":"2024-11-15T22:10:00-05:00","347":"2024-11-15T22:10:00-05:00","348":"2024-11-15T22:10:00-05:00","349":"2024-11-15T22:10:00-05:00","350":"2024-11-15T22:10:00-05:00","351":"2024-11-15T22:10:00-05:00","352":"2024-11-15T22:10:00-05:00","353":"2024-11-15T22:10:00-05:00","354":"2024-11-15T22:10:00-05:00","355":"2024-11-15T22:10:00-05:00","356":"2024-11-15T22:10:00-05:00","357":"2024-11-15T22:10:00-05:00","358":"2024-11-15T22:10:00-05:00","359":"2024-11-15T22:10:00-05:00","360":"2024-11-15T22:10:00-05:00","361":"2024-11-15T22:10:00-05:00","362":"2024-11-15T22:10:00-05:00","363":"2024-11-15T22:10:00-05:00","364":"2024-11-15T22:10:00-05:00","365":"2024-11-15T22:10:00-05:00","366":"2024-11-15T22:10:00-05:00","367":"2024-11-15T22:10:00-05:00","368":"2024-11-15T22:10:00-05:00","369":"2024-11-15T22:10:00-05:00","370":"2024-11-15T22:10:00-05:00","371":"2024-11-15T22:10:00-05:00","372":"2024-11-15T22:10:00-05:00","373":"2024-11-15T22:10:00-05:00","374":"2024-11-15T22:10:00-05:00","375":"2024-11-15T22:10:00-05:00","376":"2024-11-15T22:10:00-05:00","377":"2024-11-15T22:10:00-05:00","378":"2024-11-15T22:10:00-05:00","379":"2024-11-15T22:10:00-05:00","380":"2024-11-15T22:10:00-05:00","381":"2024-11-15T22:10:00-05:00","382":"2024-11-15T22:10:00-05:00","383":"2024-11-15T22:10:00-05:00","384":"2024-11-15T22:10:00-05:00","385":"2024-11-15T22:10:00-05:00","386":"2024-11-15T22:10:00-05:00","387":"2024-11-15T22:10:00-05:00","388":"2024-11-15T22:10:00-05:00","389":"2024-11-15T22:10:00-05:00","390":"2024-11-15T22:10:00-05:00","391":"2024-11-15T22:10:00-05:00","392":"2024-11-15T22:10:00-05:00","393":"2024-11-15T22:10:00-05:00","394":"2024-11-15T22:10:00-05:00","395":"2024-11-15T22:10:00-05:00","396":"2024-11-15T22:10:00-05:00","397":"2024-11-15T22:10:00-05:00","398":"2024-11-15T22:10:00-05:00","399":"2024-11-15T22:10:00-05:00","400":"2024-11-15T22:10:00-05:00","401":"2024-11-15T22:10:00-05:00","402":"2024-11-15T22:10:00-05:00","403":"2024-11-15T22:10:00-05:00","404":"2024-11-15T22:10:00-05:00","405":"2024-11-15T22:10:00-05:00","406":"2024-11-15T22:10:00-05:00","407":"2024-11-15T22:10:00-05:00","408":"2024-11-15T22:10:00-05:00","409":"2024-11-15T22:10:00-05:00","410":"2024-11-15T22:10:00-05:00","411":"2024-11-15T22:10:00-05:00","412":"2024-11-15T22:10:00-05:00","413":"2024-11-15T22:10:00-05:00","414":"2024-11-15T22:10:00-05:00","415":"2024-11-15T22:10:00-05:00","416":"2024-11-15T22:10:00-05:00","417":"2024-11-15T22:10:00-05:00","418":"2024-11-15T22:10:00-05:00","419":"2024-11-15T22:10:00-05:00","420":"2024-11-15T22:10:00-05:00","421":"2024-11-15T22:10:00-05:00","422":"2024-11-15T22:10:00-05:00","423":"2024-11-15T22:10:00-05:00","424":"2024-11-15T22:10:00-05:00","425":"2024-11-15T22:10:00-05:00","426":"2024-11-15T22:10:00-05:00","427":"2024-11-15T22:10:00-05:00","428":"2024-11-15T22:10:00-05:00","429":"2024-11-15T22:10:00-05:00","430":"2024-11-15T22:10:00-05:00","431":"2024-11-15T22:10:00-05:00","432":"2024-11-15T22:10:00-05:00","433":"2024-11-15T22:10:00-05:00","434":"2024-11-15T22:10:00-05:00","435":"2024-11-15T22:10:00-05:00","436":"2024-11-15T22:10:00-05:00","437":"2024-11-15T22:10:00-05:00","438":"2024-11-15T22:10:00-05:00","439":"2024-11-15T22:10:00-05:00","440":"2024-11-15T22:10:00-05:00","441":"2024-11-15T22:10:00-05:00","442":"2024-11-15T22:10:00-05:00","443":"2024-11-15T22:10:00-05:00","444":"2024-11-15T22:10:00-05:00","445":"2024-11-15T22:10:00-05:00","446":"2024-11-15T22:10:00-05:00","447":"2024-11-15T22:10:00-05:00","448":"2024-11-15T22:10:00-05:00","449":"2024-11-15T22:10:00-05:00","450":"2024-11-15T22:10:00-05:00","451":"2024-11-15T22:10:00-05:00","452":"2024-11-15T22:10:00-05:00","453":"2024-11-15T22:10:00-05:00","454":"2024-11-15T22:10:00-05:00","455":"2024-11-15T22:10:00-05:00","456":"2024-11-15T22:10:00-05:00","457":"2024-11-15T22:10:00-05:00","458":"2024-11-15T22:10:00-05:00","459":"2024-11-15T22:10:00-05:00","460":"2024-11-15T22:10:00-05:00","461":"2024-11-15T22:10:00-05:00","462":"2024-11-15T22:10:00-05:00","463":"2024-11-15T22:10:00-05:00","464":"2024-11-15T22:10:00-05:00","465":"2024-11-15T22:10:00-05:00","466":"2024-11-15T22:10:00-05:00","467":"2024-11-15T22:10:00-05:00","468":"2024-11-15T22:10:00-05:00","469":"2024-11-15T22:10:00-05:00","470":"2024-11-15T22:10:00-05:00","471":"2024-11-15T22:10:00-05:00","472":"2024-11-15T22:10:00-05:00","473":"2024-11-15T22:10:00-05:00","474":"2024-11-15T22:10:00-05:00","475":"2024-11-15T22:10:00-05:00","476":"2024-11-15T22:10:00-05:00","477":"2024-11-15T22:10:00-05:00","478":"2024-11-15T22:10:00-05:00","479":"2024-11-15T22:10:00-05:00","480":"2024-11-15T22:10:00-05:00","481":"2024-11-15T22:10:00-05:00","482":"2024-11-15T22:10:00-05:00","483":"2024-11-15T22:10:00-05:00","484":"2024-11-15T22:10:00-05:00","485":"2024-11-15T22:10:00-05:00","486":"2024-11-15T22:10:00-05:00","487":"2024-11-15T22:10:00-05:00","488":"2024-11-15T22:10:00-05:00","489":"2024-11-15T22:10:00-05:00","490":"2024-11-15T22:10:00-05:00","491":"2024-11-15T22:10:00-05:00","492":"2024-11-15T22:10:00-05:00","493":"2024-11-15T22:10:00-05:00","494":"2024-11-15T22:10:00-05:00","495":"2024-11-15T22:10:00-05:00","496":"2024-11-15T22:10:00-05:00","497":"2024-11-15T22:10:00-05:00","498":"2024-11-15T22:10:00-05:00","499":"2024-11-15T22:10:00-05:00","500":"2024-11-15T22:10:00-05:00","501":"2024-11-15T22:10:00-05:00","502":"2024-11-15T22:10:00-05:00","503":"2024-11-15T22:10:00-05:00","504":"2024-11-15T22:10:00-05:00","505":"2024-11-15T22:10:00-05:00","506":"2024-11-15T22:10:00-05:00","507":"2024-11-15T22:10:00-05:00","508":"2024-11-15T22:10:00-05:00","509":"2024-11-15T22:10:00-05:00","510":"2024-11-15T22:10:00-05:00","511":"2024-11-15T22:10:00-05:00","512":"2024-11-15T22:10:00-05:00","513":"2024-11-15T22:10:00-05:00","514":"2024-11-15T22:10:00-05:00","515":"2024-11-15T22:10:00-05:00","516":"2024-11-15T22:10:00-05:00","517":"2024-11-15T22:10:00-05:00","518":"2024-11-15T22:10:00-05:00","519":"2024-11-15T22:10:00-05:00","520":"2024-11-15T22:10:00-05:00","521":"2024-11-15T22:10:00-05:00","522":"2024-11-15T22:10:00-05:00","523":"2024-11-15T22:10:00-05:00","524":"2024-11-15T22:10:00-05:00","525":"2024-11-15T22:10:00-05:00","526":"2024-11-15T22:10:00-05:00","527":"2024-11-15T22:10:00-05:00","528":"2024-11-15T22:10:00-05:00","529":"2024-11-15T22:10:00-05:00","530":"2024-11-15T22:10:00-05:00","531":"2024-11-15T22:10:00-05:00","532":"2024-11-15T22:10:00-05:00","533":"2024-11-15T22:10:00-05:00","534":"2024-11-15T22:10:00-05:00","535":"2024-11-15T22:10:00-05:00","536":"2024-11-15T22:10:00-05:00","537":"2024-11-15T22:10:00-05:00","538":"2024-11-15T22:10:00-05:00","539":"2024-11-15T22:10:00-05:00","540":"2024-11-15T22:10:00-05:00","541":"2024-11-15T22:10:00-05:00","542":"2024-11-15T22:10:00-05:00","543":"2024-11-15T22:10:00-05:00","544":"2024-11-15T22:10:00-05:00","545":"2024-11-15T22:10:00-05:00","546":"2024-11-15T22:10:00-05:00","547":"2024-11-15T22:10:00-05:00","548":"2024-11-15T22:10:00-05:00","549":"2024-11-15T22:10:00-05:00","550":"2024-11-15T22:10:00-05:00","551":"2024-11-15T22:10:00-05:00","552":"2024-11-15T22:10:00-05:00","553":"2024-11-15T22:10:00-05:00","554":"2024-11-15T22:10:00-05:00","555":"2024-11-15T22:10:00-05:00","556":"2024-11-15T22:10:00-05:00","557":"2024-11-15T22:10:00-05:00","558":"2024-11-15T22:10:00-05:00","559":"2024-11-15T22:10:00-05:00","560":"2024-11-15T22:10:00-05:00","561":"2024-11-15T22:10:00-05:00","562":"2024-11-15T22:10:00-05:00","563":"2024-11-15T22:10:00-05:00","564":"2024-11-15T22:10:00-05:00","565":"2024-11-15T22:10:00-05:00","566":"2024-11-15T22:10:00-05:00","567":"2024-11-15T22:10:00-05:00","568":"2024-11-15T22:10:00-05:00","569":"2024-11-15T22:10:00-05:00","570":"2024-11-15T22:10:00-05:00","571":"2024-11-15T22:10:00-05:00","572":"2024-11-15T22:10:00-05:00","573":"2024-11-15T22:10:00-05:00","574":"2024-11-15T22:10:00-05:00","575":"2024-11-15T22:10:00-05:00","576":"2024-11-15T22:10:00-05:00","577":"2024-11-15T22:10:00-05:00","578":"2024-11-15T22:10:00-05:00","579":"2024-11-15T22:10:00-05:00","580":"2024-11-15T22:10:00-05:00","581":"2024-11-15T22:10:00-05:00","582":"2024-11-15T22:10:00-05:00","583":"2024-11-15T22:10:00-05:00","584":"2024-11-15T22:10:00-05:00","585":"2024-11-15T22:10:00-05:00","586":"2024-11-15T22:10:00-05:00","587":"2024-11-15T22:10:00-05:00","588":"2024-11-15T22:10:00-05:00","589":"2024-11-15T22:10:00-05:00","590":"2024-11-15T22:10:00-05:00","591":"2024-11-15T22:10:00-05:00","592":"2024-11-15T22:10:00-05:00","593":"2024-11-15T22:10:00-05:00"},"status":{"0":"pre_game","1":"pre_game","2":"pre_game","3":"pre_game","4":"pre_game","5":"pre_game","6":"pre_game","7":"pre_game","8":"pre_game","9":"pre_game","10":"pre_game","11":"pre_game","12":"pre_game","13":"pre_game","14":"pre_game","15":"pre_game","16":"pre_game","17":"pre_game","18":"pre_game","19":"pre_game","20":"pre_game","21":"pre_game","22":"pre_game","23":"pre_game","24":"pre_game","25":"pre_game","26":"pre_game","27":"pre_game","28":"pre_game","29":"pre_game","30":"pre_game","31":"pre_game","32":"pre_game","33":"pre_game","34":"pre_game","35":"pre_game","36":"pre_game","37":"pre_game","38":"pre_game","39":"pre_game","40":"pre_game","41":"pre_game","42":"pre_game","43":"pre_game","44":"pre_game","45":"pre_game","46":"pre_game","47":"pre_game","48":"pre_game","49":"pre_game","50":"pre_game","51":"pre_game","52":"pre_game","53":"pre_game","54":"pre_game","55":"pre_game","56":"pre_game","57":"pre_game","58":"pre_game","59":"pre_game","60":"pre_game","61":"pre_game","62":"pre_game","63":"pre_game","64":"pre_game","65":"pre_game","66":"pre_game","67":"pre_game","68":"pre_game","69":"pre_game","70":"pre_game","71":"pre_game","72":"pre_game","73":"pre_game","74":"pre_game","75":"pre_game","76":"pre_game","77":"pre_game","78":"pre_game","79":"pre_game","80":"pre_game","81":"pre_game","82":"pre_game","83":"pre_game","84":"pre_game","85":"pre_game","86":"pre_game","87":"pre_game","88":"pre_game","89":"pre_game","90":"pre_game","91":"pre_game","92":"pre_game","93":"pre_game","94":"pre_game","95":"pre_game","96":"pre_game","97":"pre_game","98":"pre_game","99":"pre_game","100":"pre_game","101":"pre_game","102":"pre_game","103":"pre_game","104":"pre_game","105":"pre_game","106":"pre_game","107":"pre_game","108":"pre_game","109":"pre_game","110":"pre_game","111":"pre_game","112":"pre_game","113":"pre_game","114":"pre_game","115":"pre_game","116":"pre_game","117":"pre_game","118":"pre_game","119":"pre_game","120":"pre_game","121":"pre_game","122":"pre_game","123":"pre_game","124":"pre_game","125":"pre_game","126":"pre_game","127":"pre_game","128":"pre_game","129":"pre_game","130":"pre_game","131":"pre_game","132":"pre_game","133":"pre_game","134":"pre_game","135":"pre_game","136":"pre_game","137":"pre_game","138":"pre_game","139":"pre_game","140":"pre_game","141":"pre_game","142":"pre_game","143":"pre_game","144":"pre_game","145":"pre_game","146":"pre_game","147":"pre_game","148":"pre_game","149":"pre_game","150":"pre_game","151":"pre_game","152":"pre_game","153":"pre_game","154":"pre_game","155":"pre_game","156":"pre_game","157":"pre_game","158":"pre_game","159":"pre_game","160":"pre_game","161":"pre_game","162":"pre_game","163":"pre_game","164":"pre_game","165":"pre_game","166":"pre_game","167":"pre_game","168":"pre_game","169":"pre_game","170":"pre_game","171":"pre_game","172":"pre_game","173":"pre_game","174":"pre_game","175":"pre_game","176":"pre_game","177":"pre_game","178":"pre_game","179":"pre_game","180":"pre_game","181":"pre_game","182":"pre_game","183":"pre_game","184":"pre_game","185":"pre_game","186":"pre_game","187":"pre_game","188":"pre_game","189":"pre_game","190":"pre_game","191":"pre_game","192":"pre_game","193":"pre_game","194":"pre_game","195":"pre_game","196":"pre_game","197":"pre_game","198":"pre_game","199":"pre_game","200":"pre_game","201":"pre_game","202":"pre_game","203":"pre_game","204":"pre_game","205":"pre_game","206":"pre_game","207":"pre_game","208":"pre_game","209":"pre_game","210":"pre_game","211":"pre_game","212":"pre_game","213":"pre_game","214":"pre_game","215":"pre_game","216":"pre_game","217":"pre_game","218":"pre_game","219":"pre_game","220":"pre_game","221":"pre_game","222":"pre_game","223":"pre_game","224":"pre_game","225":"pre_game","226":"pre_game","227":"pre_game","228":"pre_game","229":"pre_game","230":"pre_game","231":"pre_game","232":"pre_game","233":"pre_game","234":"pre_game","235":"pre_game","236":"pre_game","237":"pre_game","238":"pre_game","239":"pre_game","240":"pre_game","241":"pre_game","242":"pre_game","243":"pre_game","244":"pre_game","245":"pre_game","246":"pre_game","247":"pre_game","248":"pre_game","249":"pre_game","250":"pre_game","251":"pre_game","252":"pre_game","253":"pre_game","254":"pre_game","255":"pre_game","256":"pre_game","257":"pre_game","258":"pre_game","259":"pre_game","260":"pre_game","261":"pre_game","262":"pre_game","263":"pre_game","264":"pre_game","265":"pre_game","266":"pre_game","267":"pre_game","268":"pre_game","269":"pre_game","270":"pre_game","271":"pre_game","272":"pre_game","273":"pre_game","274":"pre_game","275":"pre_game","276":"pre_game","277":"pre_game","278":"pre_game","279":"pre_game","280":"pre_game","281":"pre_game","282":"pre_game","283":"pre_game","284":"pre_game","285":"pre_game","286":"pre_game","287":"pre_game","288":"pre_game","289":"pre_game","290":"pre_game","291":"pre_game","292":"pre_game","293":"pre_game","294":"pre_game","295":"pre_game","296":"pre_game","297":"pre_game","298":"pre_game","299":"pre_game","300":"pre_game","301":"pre_game","302":"pre_game","303":"pre_game","304":"pre_game","305":"pre_game","306":"pre_game","307":"pre_game","308":"pre_game","309":"pre_game","310":"pre_game","311":"pre_game","312":"pre_game","313":"pre_game","314":"pre_game","315":"pre_game","316":"pre_game","317":"pre_game","318":"pre_game","319":"pre_game","320":"pre_game","321":"pre_game","322":"pre_game","323":"pre_game","324":"pre_game","325":"pre_game","326":"pre_game","327":"pre_game","328":"pre_game","329":"pre_game","330":"pre_game","331":"pre_game","332":"pre_game","333":"pre_game","334":"pre_game","335":"pre_game","336":"pre_game","337":"pre_game","338":"pre_game","339":"pre_game","340":"pre_game","341":"pre_game","342":"pre_game","343":"pre_game","344":"pre_game","345":"pre_game","346":"pre_game","347":"pre_game","348":"pre_game","349":"pre_game","350":"pre_game","351":"pre_game","352":"pre_game","353":"pre_game","354":"pre_game","355":"pre_game","356":"pre_game","357":"pre_game","358":"pre_game","359":"pre_game","360":"pre_game","361":"pre_game","362":"pre_game","363":"pre_game","364":"pre_game","365":"pre_game","366":"pre_game","367":"pre_game","368":"pre_game","369":"pre_game","370":"pre_game","371":"pre_game","372":"pre_game","373":"pre_game","374":"pre_game","375":"pre_game","376":"pre_game","377":"pre_game","378":"pre_game","379":"pre_game","380":"pre_game","381":"pre_game","382":"pre_game","383":"pre_game","384":"pre_game","385":"pre_game","386":"pre_game","387":"pre_game","388":"pre_game","389":"pre_game","390":"pre_game","391":"pre_game","392":"pre_game","393":"pre_game","394":"pre_game","395":"pre_game","396":"pre_game","397":"pre_game","398":"pre_game","399":"pre_game","400":"pre_game","401":"pre_game","402":"pre_game","403":"pre_game","404":"pre_game","405":"pre_game","406":"pre_game","407":"pre_game","408":"pre_game","409":"pre_game","410":"pre_game","411":"pre_game","412":"pre_game","413":"pre_game","414":"pre_game","415":"pre_game","416":"pre_game","417":"pre_game","418":"pre_game","419":"pre_game","420":"pre_game","421":"pre_game","422":"pre_game","423":"pre_game","424":"pre_game","425":"pre_game","426":"pre_game","427":"pre_game","428":"pre_game","429":"pre_game","430":"pre_game","431":"pre_game","432":"pre_game","433":"pre_game","434":"pre_game","435":"pre_game","436":"pre_game","437":"pre_game","438":"pre_game","439":"pre_game","440":"pre_game","441":"pre_game","442":"pre_game","443":"pre_game","444":"pre_game","445":"pre_game","446":"pre_game","447":"pre_game","448":"pre_game","449":"pre_game","450":"pre_game","451":"pre_game","452":"pre_game","453":"pre_game","454":"pre_game","455":"pre_game","456":"pre_game","457":"pre_game","458":"pre_game","459":"pre_game","460":"pre_game","461":"pre_game","462":"pre_game","463":"pre_game","464":"pre_game","465":"pre_game","466":"pre_game","467":"pre_game","468":"pre_game","469":"pre_game","470":"pre_game","471":"pre_game","472":"pre_game","473":"pre_game","474":"pre_game","475":"pre_game","476":"pre_game","477":"pre_game","478":"pre_game","479":"pre_game","480":"pre_game","481":"pre_game","482":"pre_game","483":"pre_game","484":"pre_game","485":"pre_game","486":"pre_game","487":"pre_game","488":"pre_game","489":"pre_game","490":"pre_game","491":"pre_game","492":"pre_game","493":"pre_game","494":"pre_game","495":"pre_game","496":"pre_game","497":"pre_game","498":"pre_game","499":"pre_game","500":"pre_game","501":"pre_game","502":"pre_game","503":"pre_game","504":"pre_game","505":"pre_game","506":"pre_game","507":"pre_game","508":"pre_game","509":"pre_game","510":"pre_game","511":"pre_game","512":"pre_game","513":"pre_game","514":"pre_game","515":"pre_game","516":"pre_game","517":"pre_game","518":"pre_game","519":"pre_game","520":"pre_game","521":"pre_game","522":"pre_game","523":"pre_game","524":"pre_game","525":"pre_game","526":"pre_game","527":"pre_game","528":"pre_game","529":"pre_game","530":"pre_game","531":"pre_game","532":"pre_game","533":"pre_game","534":"pre_game","535":"pre_game","536":"pre_game","537":"pre_game","538":"pre_game","539":"pre_game","540":"pre_game","541":"pre_game","542":"pre_game","543":"pre_game","544":"pre_game","545":"pre_game","546":"pre_game","547":"pre_game","548":"pre_game","549":"pre_game","550":"pre_game","551":"pre_game","552":"pre_game","553":"pre_game","554":"pre_game","555":"pre_game","556":"pre_game","557":"pre_game","558":"pre_game","559":"pre_game","560":"pre_game","561":"pre_game","562":"pre_game","563":"pre_game","564":"pre_game","565":"pre_game","566":"pre_game","567":"pre_game","568":"pre_game","569":"pre_game","570":"pre_game","571":"pre_game","572":"pre_game","573":"pre_game","574":"pre_game","575":"pre_game","576":"pre_game","577":"pre_game","578":"pre_game","579":"pre_game","580":"pre_game","581":"pre_game","582":"pre_game","583":"pre_game","584":"pre_game","585":"pre_game","586":"pre_game","587":"pre_game","588":"pre_game","589":"pre_game","590":"pre_game","591":"pre_game","592":"pre_game","593":"pre_game"},"name":{"0":"Jalen Green + James Harden","1":"Alperen Sengun + Ivica Zubac","2":"Fred VanVleet + Norman Powell","3":"Devin Booker + Shai Gilgeous-Alexander","4":"Tyus Jones + Shai Gilgeous-Alexander","5":"Anthony Edwards + De'Aaron Fox","6":"Rudy Gobert + Domantas Sabonis","7":"Anthony Edwards + Domantas Sabonis","8":"Stephen Curry + Jaren Jackson Jr.","9":"Draymond Green + Zach Edey","10":"Stephen Curry + Jaren Jackson Jr.","11":"James Harden","12":"James Harden","13":"James Harden","14":"James Harden","15":"James Harden","16":"James Harden","17":"James Harden","18":"James Harden","19":"James Harden","20":"Jalen Green","21":"Jalen Green","22":"Jalen Green","23":"Jalen Green","24":"Jalen Green","25":"Jalen Green","26":"Jalen Green","27":"Jalen Green","28":"Jalen Green","29":"Jalen Green","30":"Norman Powell","31":"Norman Powell","32":"Norman Powell","33":"Norman Powell","34":"Norman Powell","35":"Norman Powell","36":"Norman Powell","37":"Norman Powell","38":"Alperen Sengun","39":"Alperen Sengun","40":"Alperen Sengun","41":"Alperen Sengun","42":"Alperen Sengun","43":"Alperen Sengun","44":"Alperen Sengun","45":"Alperen Sengun","46":"Alperen Sengun","47":"Alperen Sengun","48":"Alperen Sengun","49":"Ivica Zubac","50":"Ivica Zubac","51":"Ivica Zubac","52":"Ivica Zubac","53":"Ivica Zubac","54":"Ivica Zubac","55":"Ivica Zubac","56":"Ivica Zubac","57":"Fred VanVleet","58":"Fred VanVleet","59":"Fred VanVleet","60":"Fred VanVleet","61":"Fred VanVleet","62":"Fred VanVleet","63":"Fred VanVleet","64":"Fred VanVleet","65":"Fred VanVleet","66":"Fred VanVleet","67":"Derrick Jones Jr.","68":"Derrick Jones Jr.","69":"Dillon Brooks","70":"Dillon Brooks","71":"Dillon Brooks","72":"Dillon Brooks","73":"Jabari Smith Jr.","74":"Jabari Smith Jr.","75":"Jabari Smith Jr.","76":"Jabari Smith Jr.","77":"Jabari Smith Jr.","78":"Jabari Smith Jr.","79":"Tari Eason","80":"Amen Thompson","81":"Dillon Brooks","82":"Alperen Sengun","83":"Alperen Sengun","84":"Amen Thompson","85":"Alperen Sengun","86":"Amen Thompson","87":"Alperen Sengun","88":"Dillon Brooks","89":"Alperen Sengun","90":"Amen Thompson","91":"Alperen Sengun","92":"Tari Eason","93":"Tari Eason","94":"Jalen Green","95":"Jalen Green","96":"Fred VanVleet","97":"Jabari Smith Jr.","98":"Jalen Green","99":"Jabari Smith Jr.","100":"Dillon Brooks","101":"Jalen Green","102":"Alperen Sengun","103":"Jalen Green","104":"Dillon Brooks","105":"Dillon Brooks","106":"Fred VanVleet","107":"Jabari Smith Jr.","108":"Fred VanVleet","109":"Jalen Green","110":"Jabari Smith Jr.","111":"Fred VanVleet","112":"Fred VanVleet","113":"Dillon Brooks","114":"Alperen Sengun","115":"Alperen Sengun","116":"Alperen Sengun","117":"Alperen Sengun","118":"Alperen Sengun","119":"Alperen Sengun","120":"Tari Eason","121":"Tari Eason","122":"Tari Eason","123":"Tari Eason","124":"Jalen Green","125":"Jalen Green","126":"Jalen Green","127":"Jalen Green","128":"Jalen Green","129":"Dillon Brooks","130":"Fred VanVleet","131":"Dillon Brooks","132":"Fred VanVleet","133":"Fred VanVleet","134":"Jalen Green","135":"Fred VanVleet","136":"Jabari Smith Jr.","137":"Fred VanVleet","138":"Jabari Smith Jr.","139":"Fred VanVleet","140":"Dillon Brooks","141":"Jalen Green","142":"Fred VanVleet","143":"Fred VanVleet","144":"Fred VanVleet","145":"Fred VanVleet","146":"Jabari Smith Jr.","147":"Dillon Brooks","148":"Jabari Smith Jr.","149":"Alperen Sengun","150":"Amen Thompson","151":"Alperen Sengun","152":"Jamal Murray","153":"Jamal Murray","154":"Jamal Murray","155":"Jamal Murray","156":"Jamal Murray","157":"Jamal Murray","158":"Jamal Murray","159":"Brandon Boston","160":"Brandon Boston","161":"Brandon Boston","162":"Brandon Boston","163":"Michael Porter Jr.","164":"Michael Porter Jr.","165":"Michael Porter Jr.","166":"Michael Porter Jr.","167":"Brandon Ingram","168":"Brandon Ingram","169":"Brandon Ingram","170":"Brandon Ingram","171":"Brandon Ingram","172":"Brandon Ingram","173":"Brandon Ingram","174":"Christian Braun","175":"Christian Braun","176":"Trey Murphy III","177":"Trey Murphy III","178":"Trey Murphy III","179":"Trey Murphy III","180":"Russell Westbrook","181":"Russell Westbrook","182":"Russell Westbrook","183":"Russell Westbrook","184":"Russell Westbrook","185":"Russell Westbrook","186":"Yves Missi","187":"Yves Missi","188":"Yves Missi","189":"Peyton Watson","190":"Peyton Watson","191":"Peyton Watson","192":"Trey Murphy III","193":"Trey Murphy III","194":"Trey Murphy III","195":"Trey Murphy III","196":"Brandon Ingram","197":"Brandon Ingram","198":"Brandon Ingram","199":"Brandon Ingram","200":"Michael Porter Jr.","201":"Christian Braun","202":"Jamal Murray","203":"Brandon Ingram","204":"Trey Murphy III","205":"Trey Murphy III","206":"Brandon Ingram","207":"Brandon Ingram","208":"Trey Murphy III","209":"Trey Murphy III","210":"Devin Booker","211":"Devin Booker","212":"Devin Booker","213":"Devin Booker","214":"Devin Booker","215":"Devin Booker","216":"Shai Gilgeous-Alexander","217":"Shai Gilgeous-Alexander","218":"Shai Gilgeous-Alexander","219":"Shai Gilgeous-Alexander","220":"Shai Gilgeous-Alexander","221":"Tyus Jones","222":"Tyus Jones","223":"Tyus Jones","224":"Tyus Jones","225":"Tyus Jones","226":"Tyus Jones","227":"Jalen Williams","228":"Jalen Williams","229":"Jalen Williams","230":"Jalen Williams","231":"Jalen Williams","232":"Jusuf Nurkic","233":"Jusuf Nurkic","234":"Jusuf Nurkic","235":"Jusuf Nurkic","236":"Jusuf Nurkic","237":"Luguentz Dort","238":"Luguentz Dort","239":"Luguentz Dort","240":"Luguentz Dort","241":"Isaiah Joe","242":"Cason Wallace","243":"Devin Booker","244":"Devin Booker","245":"Luguentz Dort","246":"Luguentz Dort","247":"Shai Gilgeous-Alexander","248":"Luguentz Dort","249":"Luguentz Dort","250":"Shai Gilgeous-Alexander","251":"Luguentz Dort","252":"Shai Gilgeous-Alexander","253":"Tyus Jones","254":"Jusuf Nurkic","255":"Tyus Jones","256":"Tyus Jones","257":"Jalen Williams","258":"Jalen Williams","259":"Jalen Williams","260":"Devin Booker","261":"Devin Booker","262":"Devin Booker","263":"Devin Booker","264":"Jusuf Nurkic","265":"Jalen Williams","266":"Jusuf Nurkic","267":"Tyus Jones","268":"Shai Gilgeous-Alexander","269":"Shai Gilgeous-Alexander","270":"Shai Gilgeous-Alexander","271":"Tyus Jones","272":"Tyus Jones","273":"Tyus Jones","274":"Tyus Jones","275":"Luguentz Dort","276":"Luguentz Dort","277":"Shai Gilgeous-Alexander","278":"Jalen Williams","279":"Jalen Williams","280":"Shai Gilgeous-Alexander","281":"Jalen Williams","282":"Devin Booker","283":"Devin Booker","284":"Jusuf Nurkic","285":"Jusuf Nurkic","286":"Devin Booker","287":"Jusuf Nurkic","288":"Devin Booker","289":"Devin Booker","290":"Shai Gilgeous-Alexander","291":"Anthony Edwards","292":"Anthony Edwards","293":"Anthony Edwards","294":"Anthony Edwards","295":"Anthony Edwards","296":"Anthony Edwards","297":"Anthony Edwards","298":"Anthony Edwards","299":"Anthony Edwards","300":"Anthony Edwards","301":"Anthony Edwards","302":"Anthony Edwards","303":"De'Aaron Fox","304":"De'Aaron Fox","305":"De'Aaron Fox","306":"De'Aaron Fox","307":"De'Aaron Fox","308":"De'Aaron Fox","309":"De'Aaron Fox","310":"De'Aaron Fox","311":"De'Aaron Fox","312":"De'Aaron Fox","313":"De'Aaron Fox","314":"De'Aaron Fox","315":"Julius Randle","316":"Julius Randle","317":"Julius Randle","318":"Julius Randle","319":"Julius Randle","320":"Julius Randle","321":"Julius Randle","322":"Julius Randle","323":"Julius Randle","324":"Julius Randle","325":"Julius Randle","326":"Domantas Sabonis","327":"Domantas Sabonis","328":"Domantas Sabonis","329":"Domantas Sabonis","330":"Domantas Sabonis","331":"Domantas Sabonis","332":"Domantas Sabonis","333":"Domantas Sabonis","334":"Domantas Sabonis","335":"Domantas Sabonis","336":"Domantas Sabonis","337":"Rudy Gobert","338":"Rudy Gobert","339":"Rudy Gobert","340":"Rudy Gobert","341":"Rudy Gobert","342":"Rudy Gobert","343":"Rudy Gobert","344":"Rudy Gobert","345":"Keegan Murray","346":"Keegan Murray","347":"Keegan Murray","348":"Keegan Murray","349":"Keegan Murray","350":"Keegan Murray","351":"Keegan Murray","352":"Keegan Murray","353":"Jaden McDaniels","354":"Jaden McDaniels","355":"Jaden McDaniels","356":"Jaden McDaniels","357":"Jaden McDaniels","358":"Jaden McDaniels","359":"Jaden McDaniels","360":"Kevin Huerter","361":"Kevin Huerter","362":"Kevin Huerter","363":"Kevin Huerter","364":"Kevin Huerter","365":"Kevin Huerter","366":"Kevin Huerter","367":"Kevin Huerter","368":"Kevin Huerter","369":"Kevin Huerter","370":"Mike Conley","371":"Mike Conley","372":"Mike Conley","373":"Mike Conley","374":"Donte DiVincenzo","375":"Donte DiVincenzo","376":"Donte DiVincenzo","377":"Donte DiVincenzo","378":"Naz Reid","379":"Naz Reid","380":"Naz Reid","381":"Naz Reid","382":"Naz Reid","383":"Nickeil Alexander-Walker","384":"Nickeil Alexander-Walker","385":"Nickeil Alexander-Walker","386":"Nickeil Alexander-Walker","387":"Julius Randle","388":"Jaden McDaniels","389":"Kevin Huerter","390":"Anthony Edwards","391":"Anthony Edwards","392":"Domantas Sabonis","393":"De'Aaron Fox","394":"Anthony Edwards","395":"Anthony Edwards","396":"De'Aaron Fox","397":"De'Aaron Fox","398":"De'Aaron Fox","399":"Anthony Edwards","400":"Anthony Edwards","401":"Anthony Edwards","402":"Mike Conley","403":"Rudy Gobert","404":"Rudy Gobert","405":"Rudy Gobert","406":"Kevin Huerter","407":"Kevin Huerter","408":"Rudy Gobert","409":"Kevin Huerter","410":"Mike Conley","411":"Keegan Murray","412":"Mike Conley","413":"Mike Conley","414":"Kevin Huerter","415":"Kevin Huerter","416":"Domantas Sabonis","417":"Domantas Sabonis","418":"Jaden McDaniels","419":"Jaden McDaniels","420":"Julius Randle","421":"Jaden McDaniels","422":"Keegan Murray","423":"Keegan Murray","424":"Julius Randle","425":"Julius Randle","426":"Jaden McDaniels","427":"Julius Randle","428":"Keegan Murray","429":"Julius Randle","430":"Keegan Murray","431":"Domantas Sabonis","432":"Jaden McDaniels","433":"Domantas Sabonis","434":"Jaden McDaniels","435":"Anthony Edwards","436":"Domantas Sabonis","437":"Anthony Edwards","438":"Keegan Murray","439":"Jaden McDaniels","440":"Jaden McDaniels","441":"De'Aaron Fox","442":"Domantas Sabonis","443":"De'Aaron Fox","444":"De'Aaron Fox","445":"De'Aaron Fox","446":"De'Aaron Fox","447":"Anthony Edwards","448":"Anthony Edwards","449":"Domantas Sabonis","450":"De'Aaron Fox","451":"Anthony Edwards","452":"Rudy Gobert","453":"Rudy Gobert","454":"Domantas Sabonis","455":"Julius Randle","456":"Mike Conley","457":"Jaden McDaniels","458":"Kevin Huerter","459":"Domantas Sabonis","460":"Mike Conley","461":"Domantas Sabonis","462":"Kevin Huerter","463":"Kevin Huerter","464":"Mike Conley","465":"Rudy Gobert","466":"Mike Conley","467":"Jaden McDaniels","468":"Keegan Murray","469":"Keegan Murray","470":"Jaren Jackson Jr.","471":"Jaren Jackson Jr.","472":"Jaren Jackson Jr.","473":"Jaren Jackson Jr.","474":"Jaren Jackson Jr.","475":"Jaren Jackson Jr.","476":"Stephen Curry","477":"Jaren Jackson Jr.","478":"Stephen Curry","479":"Stephen Curry","480":"Stephen Curry","481":"Stephen Curry","482":"Santi Aldama","483":"Stephen Curry","484":"Stephen Curry","485":"Stephen Curry","486":"Stephen Curry","487":"Stephen Curry","488":"Santi Aldama","489":"Santi Aldama","490":"Santi Aldama","491":"Santi Aldama","492":"Santi Aldama","493":"Santi Aldama","494":"Draymond Green","495":"Santi Aldama","496":"Andrew Wiggins","497":"Andrew Wiggins","498":"Andrew Wiggins","499":"Andrew Wiggins","500":"Andrew Wiggins","501":"Zach Edey","502":"Zach Edey","503":"Zach Edey","504":"Draymond Green","505":"Draymond Green","506":"Draymond Green","507":"Draymond Green","508":"Trayce Jackson-Davis","509":"Trayce Jackson-Davis","510":"Trayce Jackson-Davis","511":"Trayce Jackson-Davis","512":"Jonathan Kuminga","513":"Jonathan Kuminga","514":"Jonathan Kuminga","515":"Jonathan Kuminga","516":"Jonathan Kuminga","517":"Buddy Hield","518":"Buddy Hield","519":"Buddy Hield","520":"Trayce Jackson-Davis","521":"Draymond Green","522":"Buddy Hield","523":"Andrew Wiggins","524":"Jonathan Kuminga","525":"Santi Aldama","526":"Andrew Wiggins","527":"Stephen Curry","528":"Santi Aldama","529":"Santi Aldama","530":"Stephen Curry","531":"Stephen Curry","532":"Stephen Curry","533":"Stephen Curry","534":"Stephen Curry","535":"Andrew Wiggins","536":"Jaren Jackson Jr.","537":"Draymond Green","538":"Gary Payton II","539":"Andrew Wiggins","540":"Jaren Jackson Jr.","541":"Draymond Green","542":"Draymond Green","543":"Andrew Wiggins","544":"Draymond Green","545":"Stephen Curry","546":"Gary Payton II","547":"Jonathan Kuminga","548":"Draymond Green","549":"Andrew Wiggins","550":"Jaren Jackson Jr.","551":"Buddy Hield","552":"Trayce Jackson-Davis","553":"Andrew Wiggins","554":"Draymond Green","555":"Jaren Jackson Jr.","556":"Andrew Wiggins","557":"Draymond Green","558":"Santi Aldama","559":"Jaylen Wells","560":"Jaylen Wells","561":"Jaren Jackson Jr.","562":"Jaylen Wells","563":"Jaylen Wells","564":"Jaren Jackson Jr.","565":"Jaren Jackson Jr.","566":"Jaren Jackson Jr.","567":"Gary Payton II","568":"Santi Aldama","569":"Santi Aldama","570":"Stephen Curry","571":"Jaren Jackson Jr.","572":"Stephen Curry","573":"Jaren Jackson Jr.","574":"Jaylen Wells","575":"Stephen Curry","576":"Trayce Jackson-Davis","577":"Trayce Jackson-Davis","578":"Jaren Jackson Jr.","579":"Stephen Curry","580":"Stephen Curry","581":"Stephen Curry","582":"Santi Aldama","583":"Zach Edey","584":"Zach Edey","585":"Andrew Wiggins","586":"Zach Edey","587":"Zach Edey","588":"Zach Edey","589":"Draymond Green","590":"Jaren Jackson Jr.","591":"Draymond Green","592":"Jonathan Kuminga","593":"Draymond Green"}}